{"0.3.13-2": ["Wed Oct 02 2019", "Dorian Scholz", "scholz@sim.tu-darmstadt.de"], "0.3.15-1": ["Wed Oct 23 2019", "Dorian Scholz", "scholz@sim.tu-darmstadt.de"], "0.3.9-0": ["Fri Aug 03 2018", "D. Hood", "dhood@osrfoundation.org"], "0.3.13-1": ["Mon Sep 30 2019", "Dorian Scholz", "scholz@sim.tu-darmstadt.de"], "0.3.11-0": ["Wed Aug 29 2018", "D. Hood", "dhood@osrfoundation.org"], "0.3.10-0": ["Sun Aug 05 2018", "D. Hood", "dhood@osrfoundation.org"], "0.3.16-1": ["Wed Dec 04 2019", "Dorian Scholz", "scholz@sim.tu-darmstadt.de"], "0.3.12-1": ["Mon Sep 30 2019", "Dorian Scholz", "scholz@sim.tu-darmstadt.de"], "0.3.8-0": ["Wed Mar 21 2018", "D. Hood", "dhood@osrfoundation.org"], "0.3.14-1": ["Thu Oct 03 2019", "Dorian Scholz", "scholz@sim.tu-darmstadt.de"], "0.3.14-2": ["Thu Oct 03 2019", "Dorian Scholz", "scholz@sim.tu-darmstadt.de"]}